{"testsCount": 0, "failedTestsCount": 0, "tests": [], "buildWarnings": [], "buildErrors": [{"filepath": "/Users/johndemirci/Documents/XcodeApps/JDSimWatch/JDSimWatch/UI/SimulatorDetailView.swift", "columnNumber": 78, "lineNumber": 22, "message": ["expected ',' separator", "                    destination: { RunningProcessesView(simulator: simulator }, ", "                                                                             ^"], "filename": "SimulatorDetailView"}, {"filepath": "/Users/johndemirci/Documents/XcodeApps/JDSimWatch/JDSimWatch/UI/SimulatorDetailView.swift", "columnNumber": 78, "lineNumber": 22, "message": ["expected expression in list of expressions", "                    destination: { RunningProcessesView(simulator: simulator }, ", "                                                                             ^"], "filename": "SimulatorDetailView"}], "testErrors": []}
